x6c1/__init__.py
x6c1/cli.py
x6c1-3.0.0.dist-info/licenses/LICENSE
x6c1-3.0.0.dist-info/METADATA
x6c1-3.0.0.dist-info/WHEEL
x6c1-3.0.0.dist-info/entry_points.txt
x6c1-3.0.0.dist-info/top_level.txt
x6c1-3.0.0.dist-info/RECORD
